ngen_buildx/__init__.py
ngen_buildx/builder.py
ngen_buildx/cli.py
ngen_buildx/config.py
ngen_buildx-0.1.11.dist-info/METADATA
ngen_buildx-0.1.11.dist-info/WHEEL
ngen_buildx-0.1.11.dist-info/entry_points.txt
ngen_buildx-0.1.11.dist-info/top_level.txt
ngen_buildx-0.1.11.dist-info/RECORD
