Metadata-Version: 2.4
Name: ngen-buildx
Version: 0.1.11
Summary: Docker Buildx CLI wrapper with GitOps integration
Author: ngen-buildx contributors
License: MIT
Project-URL: Homepage, https://github.com/mamatnurahmat/ngen-buildx
Project-URL: Repository, https://github.com/mamatnurahmat/ngen-buildx
Project-URL: Issues, https://github.com/mamatnurahmat/ngen-buildx/issues
Keywords: cli,docker,buildx,devops,ci-cd,container
Classifier: Development Status :: 3 - Alpha
Classifier: Intended Audience :: Developers
Classifier: Programming Language :: Python :: 3
Classifier: Programming Language :: Python :: 3.7
Classifier: Programming Language :: Python :: 3.8
Classifier: Programming Language :: Python :: 3.9
Classifier: Programming Language :: Python :: 3.10
Classifier: Programming Language :: Python :: 3.11
Requires-Python: >=3.7
Requires-Dist: python-dotenv>=0.19.0
